{
 "actions": [],
 "creation": "2026-01-01 00:00:00",
 "doctype": "DocType",
 "engine": "InnoDB",
 "field_order": [
  "co_code",
  "direct",
  "indirect",
  "final"
 ],
 "fields": [
  {
   "fieldname": "co_code",
   "fieldtype": "Data",
   "label": "CO",
   "in_list_view": 1
  },
  {
   "fieldname": "direct",
   "fieldtype": "Float",
   "label": "Direct",
   "in_list_view": 1
  },
  {
   "fieldname": "indirect",
   "fieldtype": "Float",
   "label": "Indirect",
   "in_list_view": 1
  },
  {
   "fieldname": "final",
   "fieldtype": "Float",
   "label": "Final",
   "in_list_view": 1
  }
 ],
 "index_web_pages_for_search": 1,
 "links": [],
 "modified": "2026-01-01 00:00:00",
 "modified_by": "Administrator",
 "module": "OBE",
 "name": "CO Attainment Row",
 "owner": "Administrator",
 "permissions": [],
 "sort_field": "modified",
 "sort_order": "DESC",
 "states": [],
 "istable": 1
}
